[
{
        "name": "DeautherX ESP8266 Boards",
        "architecture": "esp8266",
        "version": "2.1.2",
        "category": "deautherx",
        "url": "https://github.com/spacehuhntech/arduino/releases/download/deauther-esp8266-2.7.5/deauther-esp8266-arduino-core-2.7.5.zip",
        "archiveFileName": "deauther-esp8266-arduino-core-2.7.5.zip",
        "checksum": "SHA-256:53a2117409e3948df4104e654cd5231ec156ecf6be2e37e1ec4c61f4a19814cd",
        "size": 165922125,
        "help": {
            "online": "https://github.com/BlackTechX011/DeautherX"
        },
        "boards": [
            {
                "name": "Generic ESP8266"
            },
            {
                "name": "Generic ESP8285"
            },
            {
                "name": "Adafruit Feather HUZZAH"
            },
            {
                "name": "NodeMCU"
            },
            {
                "name": "LOLIN(WEMOS) D1 mini"
            },
            {
                "name": "Maltronics Deauther"
            },
            {
                "name": "DSTIKE Deauther"
            }
        ],
        "toolsDependencies": [
            {
                "packager": "deauther",
                "version": "2.5.0-4-b40a506",
                "name": "xtensa-lx106-elf-gcc"
            },
            {
                "packager": "deauther",
                "version": "2.5.0-4-b40a506",
                "name": "mkspiffs"
            },
            {
                "packager": "deauther",
                "version": "2.5.0-4-fe5bb56",
                "name": "mklittlefs"
            },
            {
                "packager": "deauther",
                "version": "3.7.2-post1",
                "name": "python3"
            }
        ]
    }
]
